pdf2md_mcp/__init__.py
pdf2md_mcp/demo.py
pdf2md_mcp/server.py
pdf2md_mcp-0.1.1.dist-info/licenses/LICENSE
pdf2md_mcp-0.1.1.dist-info/METADATA
pdf2md_mcp-0.1.1.dist-info/WHEEL
pdf2md_mcp-0.1.1.dist-info/entry_points.txt
pdf2md_mcp-0.1.1.dist-info/top_level.txt
pdf2md_mcp-0.1.1.dist-info/RECORD
