Metadata-Version: 2.4
Name: pdf2md-mcp
Version: 0.1.1
Summary: MCP server for converting PDF files to Markdown using AI sampling
Author-email: Gavin Huang <shuminghuang@gmail.com>
License: MIT
Project-URL: Homepage, https://github.com/gavinhuang/pdf2md-mcp
Project-URL: Repository, https://github.com/gavinhuang/pdf2md-mcp.git
Project-URL: Issues, https://github.com/gavinhuang/pdf2md-mcp/issues
Keywords: mcp,pdf,markdown,conversion,ai
Classifier: Development Status :: 3 - Alpha
Classifier: Intended Audience :: Developers
Classifier: License :: OSI Approved :: MIT License
Classifier: Programming Language :: Python :: 3
Classifier: Programming Language :: Python :: 3.10
Classifier: Programming Language :: Python :: 3.11
Classifier: Programming Language :: Python :: 3.12
Requires-Python: >=3.10
License-File: LICENSE
Requires-Dist: fastmcp>=2.10.1
Requires-Dist: httpx>=0.25.0
Requires-Dist: aiofiles>=23.0.0
Requires-Dist: pathlib
Requires-Dist: typing-extensions>=4.0.0
Requires-Dist: pymupdf4llm
Provides-Extra: dev
Requires-Dist: pytest>=7.0.0; extra == "dev"
Requires-Dist: pytest-asyncio>=0.21.0; extra == "dev"
Requires-Dist: black>=23.0.0; extra == "dev"
Requires-Dist: isort>=5.12.0; extra == "dev"
Requires-Dist: flake8>=6.0.0; extra == "dev"
Requires-Dist: mypy>=1.0.0; extra == "dev"
Dynamic: license-file
